outliers_removal_101703408/outlier.py
outliers_removal08-1.0.0.dist-info/METADATA
outliers_removal08-1.0.0.dist-info/WHEEL
outliers_removal08-1.0.0.dist-info/entry_points.txt
outliers_removal08-1.0.0.dist-info/top_level.txt
outliers_removal08-1.0.0.dist-info/RECORD
