Metadata-Version: 2.1
Name: outliers-removal08
Version: 1.0.0
Summary: A Python package to remove the outliers from the dataset to improve the accuracy of the model (UCS633).
Home-page: https://github.com/Pulkitg64/outlier_removal
Author: Pulkit Gupta
Author-email: pulkitgupta64@gmail.com
License: UNKNOWN
Platform: UNKNOWN
Requires-Dist: requests
